<list>
<m type="youku" streamtype="flv" src="XMTI3Mjk3MjUy" label="001上天救命"/>
<m type="youku" streamtype="flv" src="NTM5Mjg5MjI" label="002亡命夺宝"/>
<m type="youku" streamtype="flv" src="XMTQzNzExMjIw" label="003死神傻了"/>
<m type="youku" streamtype="flv" src="XMzI0NTk5MjM2" label="004摩登仙履奇缘"/>
<m type="youku" streamtype="flv" src="XMjU5NzE0Njg=" label="005狐狸精PK采花贼"/>
<m type="youku" streamtype="flv" src="XMjkzNzgzODU2" label="006钢的琴"/>
<m type="youku" streamtype="flv" src="XODY1NTc3MDQ=" label="007波牛"/>
<m type="youku" streamtype="flv" src="XMTQ4NTI0NjA0" label="008十全九美"/>
<m type="youku" streamtype="flv" src="XMTU4OTUwNTA0" label="009奸人鬼"/>
<m type="youku" streamtype="flv" src="XNTkxNzg1MzY=" label="010女老师VS女学生"/>
<m type="youku" streamtype="flv" src="XMTkxNDgxNzM2" label="011拉面人生"/>
<m type="youku" streamtype="flv" src="XMjkyOTY0Nzg4" label="012蠢蛋搞怪秀3.5"/>
<m type="youku" streamtype="flv" src="XMTE5NzAwNzY4" label="013密宗威龙"/>
<m type="youku" streamtype="flv" src="XMTQ4MjA5Mjcy" label="014杂家小子"/>
<m type="youku" streamtype="flv" src="XMTgzNDgxNzU2" label="015猛鬼学堂"/>
<m type="youku" streamtype="flv" src="XNDI5NDAzMDg=" label="016奴隶情人"/>
<m type="youku" streamtype="flv" src="XMjkyOTc0MzY=" label="017黄飞鸿笑传"/>
<m type="youku" streamtype="flv" src="XMjk5MjgyMTIw" label="018四喜临门"/>
<m type="youku" streamtype="flv" src="XMjU1NTM1MzY4" label="019A面B面"/>
<m type="youku" streamtype="flv" src="XMTg5NDIzMTky" label="020买凶拍人"/>
<m type="youku" streamtype="flv" src="XMTg5MzY4MjEy" label="021魔幻厨房"/>
<m type="youku" streamtype="flv" src="XMzMyMjIwMjg4" label="022至尊三十六计之偷天换"/>
<m type="youku" streamtype="flv" src="XMzIwNzQyNzIw" label="023骗财骗色"/>
<m type="youku" streamtype="flv" src="XMTg5NDIxNjU2" label="024月亮的秘密"/>
<m type="youku" streamtype="flv" src="XMjA1ODIxMDQ4" label="025超级欺骗"/>
<m type="youku" streamtype="flv" src="XMjU4OTI0NjQ4" label="026年年有今日"/>
<m type="youku" streamtype="flv" src="XMTkxNTAxODky" label="027淘气少女求爱记"/>
<m type="youku" streamtype="flv" src="XMTkwMTkwNTEy" label="028决战刹马镇"/>
<m type="youku" streamtype="flv" src="XMzI5Mzk1NTc2" label="029想爱就爱"/>
<m type="youku" streamtype="flv" src="XMTYzODU2MTI4" label="030我的机器人女友"/>
<m type="youku" streamtype="flv" src="XMTgzNDg0NTky" label="031捉鬼大师"/>
<m type="youku" streamtype="flv" src="XMzA4MjQ5MDI0" label="032飞天 11版"/>
<m type="youku" streamtype="flv" src="XMzI1NzIxMTky" label="033湘江北去"/>
<m type="youku" streamtype="flv" src="XMjU1Mzg0ODY0" label="034月满轩尼诗"/>
<m type="youku" streamtype="flv" src="XMTMyMDE3NDg4" label="035姨妈的后现代生活"/>
<m type="youku" streamtype="flv" src="XMzAyOTcyMTI4" label="036上你的床"/>
<m type="youku" streamtype="flv" src="XODU2MDMyMDA=" label="037女校风波"/>
<m type="youku" streamtype="flv" src="XMzE5NzM4NDQw" label="038亲爱的你完了"/>
<m type="youku" streamtype="flv" src="XMTQwMTUyNTY4" label="039舞出我人生1"/>
<m type="youku" streamtype="flv" src="XMTk5NDg1MDIw" label="040舞出我人生2"/>
<m type="youku" streamtype="flv" src="XMjMzMzY3ODEy" label="041假发大作战"/>
<m type="youku" streamtype="flv" src="XNjYyODM2Mjg=" label="042埋伏"/>
<m type="youku" streamtype="flv" src="XMTg2MTA3Mjg0" label="043美男子"/>
<m type="youku" streamtype="flv" src="XMzIyOTcwMzAw" label="044冠军"/>
<m type="youku" streamtype="flv" src="XNzQwOTc4NjA=" label="045吉星拱照"/>
<m type="youku" streamtype="flv" src="XMjY3ODg4NzUy" label="046跳出去"/>
<m type="youku" streamtype="flv" src="XMTQxOTcyODQ0" label="047天地雄心"/>
<m type="youku" streamtype="flv" src="XMjQ4NTU4MDQ=" label="048学校的阶段"/>
<m type="youku" streamtype="flv" src="XMzI5NTgyMjQw" label="049这里有情况"/>
<m type="youku" streamtype="flv" src="XMTg5Mzk4ODI0" label="050专钓大鳄"/>
<m type="youku" streamtype="flv" src="XMjM4NTA5MTc2" label="051志明与春娇"/>
<m type="youku" streamtype="flv" src="XMTg1ODMwNjMy" label="052我们的款待"/>
<m type="youku" streamtype="flv" src="XMTQyMzg5NDE2" label="053鬼马双星"/>
<m type="youku" streamtype="flv" src="XMTg5NDExMTI4" label="054浪漫樱花"/> 
<m type="youku" streamtype="flv" src="XMjU4OTM0NzAw" label="055水浒笑传"/>
<m type="youku" streamtype="flv" src="XMjczMTg2NjQ4" label="056神算"/>
<m type="youku" streamtype="flv" src="XMTg2ODA4MTg0" label="057偷情先生"/>
<m type="youku" streamtype="flv" src="XODkxNTgzNDA=" label="058天官n福"/>
<m type="youku" streamtype="flv" src="XMTQ5NjUxNTk2" label="059武侠七公主"/>
<m type="youku" streamtype="flv" src="XMjI4MzYxNzg0" label="060小小小警察"/>
<m type="youku" streamtype="flv" src="XMjAyMDMxMzgw" label="061向我开炮"/>
<m type="youku" streamtype="flv" src="XMTIwMjUzNjYw" label="062笑八仙"/>
<m type="youku" streamtype="flv" src="XNjIwMTEzMDg=" label="063YES!一族"/>
<m type="youku" streamtype="flv" src="XMjc3Njg2Mzc2" label="064真爱满屋"/>
<m type="youku" streamtype="flv" src="XMzMwMjM5ODM2" label="065消失打看"/>
<m type="youku" streamtype="flv" src="XMjYzNzM4MDY4" label="066麻雀变王妃"/>
<m type="youku" streamtype="flv" src="XMTQ5NTc2MjA4" label="067沙滩仔与周师奶"/>
<m type="youku" streamtype="flv" src="XMTQxMzM4MzE2" label="068下一站天后"/>
<m type="youku" streamtype="flv" src="XMzY1OTY0Mjg=" label="069学校霸王花"/>
<m type="youku" streamtype="flv" src="XMTU2Njk4OTY=" label="070戏王之王"/>
<m type="youku" streamtype="flv" src="XMTIwOTE5MTE2" label="071老少爷们打鬼子"/>
<m type="youku" streamtype="flv" src="XMTgzNDg0NTky" label="072捉鬼大师"/>
<m type="youku" streamtype="flv" src="XMzQ4MTIyNDQ=" label="073亚飞与亚基"/>
<m type="youku" streamtype="flv" src="XODAxMzcxODg=" label="074我的舅舅"/>
<m type="youku" streamtype="flv" src="XMTg1ODM3MTI0" label="075小比尔号汽船"/>
<m type="youku" streamtype="flv" src="XMTU0MzQ0MDUy" label="076完全神奇"/>
<m type="youku" streamtype="flv" src="XMjE2NTM2NDM2" label="077给我一个微笑"/>
<m type="youku" streamtype="flv" src="XMjM3NzAzNDEy" label="078摇摆的婚约"/>
<m type="youku" streamtype="flv" src="XMzEwMjk5NzA0" label="079老婆是大佬1"/>
<m type="youku" streamtype="flv" src="XMTQzOTAxMDA0" label="080双肥临门"/>
<m type="youku" streamtype="flv" src="XMzMyMTg0NDEy" label="081小鬼开球"/>
<m type="youku" streamtype="flv" src="XMTg5NDE1MTMy" label="082最佳男朋友"/>
<m type="youku" streamtype="flv" src="XMTM4NTU3MDc2" label="083我要成名"/>
<m type="youku" streamtype="flv" src="XMTQ5ODM0ODc2" label="084猪扒大联盟"/>
<m type="youku" streamtype="flv" src="XMzI5MzQ3MDg0" label="085疯狂粉丝王"/>
<m type="youku" streamtype="flv" src="XMTU2MTM1MjA=" label="086一路走好"/>
<m type="youku" streamtype="flv" src="XMTU0Mzc1NDg0" label="087神秘外来客"/>
<m type="youku" streamtype="flv" src="XNTYyMDAxODQ=" label="088乘龙快婿"/>
<m type="youku" streamtype="flv" src="XMTg2MTQwMzQ0" label="089欢乐时光"/>
<m type="youku" streamtype="flv" src="XNzAxNjI2MjA=" label="090冒牌天皇"/>
<m type="youku" streamtype="flv" src="XMzA4Mjg5MTky" label="091谁说我不在乎"/>
<m type="youku" streamtype="flv" src="XMjU0NDgxNzMy" label="092我女儿的父亲"/>
<m type="youku" streamtype="flv" src="XNzc0NzQ5MTY=" label="093笑逐颜开"/>
<m type="youku" streamtype="flv" src="XOTQzMjUxMDA=" label="094小亲亲"/>
<m type="youku" streamtype="flv" src="XMTMwODgwNzg0" label="095起步停车"/>
<m type="youku" streamtype="flv" src="XMTMxNDc3OTky" label="096完美情人"/>
<m type="youku" streamtype="flv" src="XMjU4ODYzMjQw" label="097我爱一碌葛"/>
<m type="youku" streamtype="flv" src="XOTU3MzQxMjQ=" label="098香港也疯狂"/>
<m type="youku" streamtype="flv" src="XNzIzMjc3NDg=" label="099乔老爷上轿"/>
<m type="youku" streamtype="flv" src="XMjU4ODU0NjQ4" label="100花田喜事"/>
<m type="youku" streamtype="flv" src="XNjIyOTk2MjA=" label="101小娇妻"/>
<m type="youku" streamtype="flv" src="XMTg3MTc5OTIw" label="102休假日"/>
<m type="youku" streamtype="flv" src="XMjE1ODIxOTI4" label="103大搜查"/>
<m type="youku" streamtype="flv" src="XMjA1MjIyMDk2" label="104分居"/>
<m type="youku" streamtype="flv" src="XMTk4NTY5MDMy" label="105今天我休息"/>
<m type="youku" streamtype="flv" src="XMzIzMjk3MTk2" label="106恋爱恐慌症"/>
<m type="youku" streamtype="flv" src="XMjE4MTc4MjQ=" label="107莫欺少年穷"/>
<m type="youku" streamtype="flv" src="XMjU4Nzc4NjI0" label="108每当变幻时"/>
<m type="youku" streamtype="flv" src="XMjYwODAwMjg4" label="109我最棒"/>
<m type="youku" streamtype="flv" src="XMjM3NzA0MzUy" label="110我的野蛮女友2"/>
<m type="youku" streamtype="flv" src="XMTMyMTU3MDQ0" label="111巧错结良缘"/>
<m type="youku" streamtype="flv" src="XMTg3Njc3MDQ=" label="112迷离世界"/>
<m type="youku" streamtype="flv" src="XMTQ4NDg1NDQ4" label="113走着瞧"/>
<m type="youku" streamtype="flv" src="XMjUxMDMxMzk2" label="114出水芙蓉"/>
<m type="youku" streamtype="flv" src="XMjQ0MTMyMjM2" label="115大玩家"/>
<m type="youku" streamtype="flv" src="XMjc1MDQyMjY4" label="116废柴同盟"/>
<m type="youku" streamtype="flv" src="XMjU0ODcwNjU2" label="117翡翠明珠"/>
<m type="youku" streamtype="flv" src="XNzY2MzI3MzI=" label="118戆星先生"/>
<m type="youku" streamtype="flv" src="XMTg5NDEwNTEy" label="119嫁个有钱人"/>
<m type="youku" streamtype="flv" src="XMjYwNzk4NTg0" label="120绝不放过你"/>
<m type="youku" streamtype="flv" src="XMzI2MTA5OTgw" label="121嘿店"/>
<m type="youku" streamtype="flv" src="XMTE5MTE1MTI4" label="122玫瑰玫瑰我爱你"/>
<m type="youku" streamtype="flv" src="XMzExMjExODY4" label="123名花有主"/>
<m type="youku" streamtype="flv" src="XMzEwMTYxODg0" label="124人间喜剧"/>
<m type="youku" streamtype="flv" src="XMTM2MzIwNzQ0" label="125天下无双"/>
<m type="youku" streamtype="flv" src="XMTE0MzU5OTMy" label="126三对鸳鸯一张床"/>
<m type="youku" streamtype="flv" src="XMTg0MTU0ODQ0" label="127岁月神偷"/>
<m type="youku" streamtype="flv" src="XMjU4MzI3NjY0" label="128情迷大话王"/>
<m type="youku" streamtype="flv" src="XMTQ4NDk5MTMy" label="129女人不坏"/>
<m type="youku" streamtype="flv" src="XMjIzNTQ0MDA4" label="130跟我的前妻谈恋爱"/>
<m type="youku" streamtype="flv" src="XMzI3Mjg0Njg0" label="131爱情真可怕"/>
<m type="youku" streamtype="flv" src="XMTQ1MzQ0MDQ0" label="132宝贝和我"/>
<m type="youku" streamtype="flv" src="XMjYwMjI2Mjg4" label="133刺客公敌"/>
<m type="youku" streamtype="flv" src="XMjU4ODk0Njgw" label="134大赢家"/>
<m type="youku" streamtype="flv" src="XMTkyODAwNDEy" label="135非常商"/>
<m type="youku" streamtype="flv" src="XMzQwMzYyNzc2" label="136鬼马智多星"/>
<m type="youku" streamtype="flv" src="XMTUzMzAyMjA0" label="137风尘三侠"/>
<m type="youku" streamtype="flv" src="XMTQ0MDIzMzcy" label="138火星没事"/>
<m type="youku" streamtype="flv" src="XMTE0OTc0NDAw" label="139开心勿语"/>
<m type="youku" streamtype="flv" src="XMzM5MDA5NTA0" label="140烂赌英雄"/>
<m type="youku" streamtype="flv" src="XMzIwNTMxMTIw" label="141猛男滚死队"/>
<m type="youku" streamtype="flv" src="XMTA1NTg4OTQ4" label="142女男变错身"/>
<m type="youku" streamtype="flv" src="XMTE1MjY5NjI4" label="143失业皇帝"/>
<m type="youku" streamtype="flv" src="XMjQ0OTE0OTAw" label="144瘦虎肥龙"/>
<m type="youku" streamtype="flv" src="XMjk0OTIzNjY0" label="145三毛从军记"/>
<m type="youku" streamtype="flv" src="XMjU0NTIwOTAw" label="146天兵机车班长"/>
<m type="youku" streamtype="flv" src="XMzIwNDU2MTI4" label="147我左眼见到鬼"/>
<m type="youku" streamtype="flv" src="XMjA3OTA3MjEy" label="148我的失忆男友"/>
<m type="youku" streamtype="flv" src="XMzQxMzIwODAw" label="149夜夜伴肥娇"/>
<m type="youku" streamtype="flv" src="XMzI3MzQxMDk2" label="150我的老婆是大佬3"/>
<m type="youku" streamtype="flv" src="XMTUxMDgyMDMy" label="151逃学英雄传"/>
<m type="youku" streamtype="flv" src="XMjY2NDE3MzA4" label="152云下的日子"/>
<m type="youku" streamtype="flv" src="XMjYwMjA2ODIw" label="153保镖"/>
<m type="youku" streamtype="flv" src="XMTkzMDI2MjAw" label="154爱情保险"/>
<m type="youku" streamtype="flv" src="XMTgzNDI3MjA0" label="155痴情快婿"/>
<m type="youku" streamtype="flv" src="XMTQwMTU0Nzk2" label="156高兴"/>
<m type="youku" streamtype="flv" src="XMTQwNzI1MTAw" label="157四大金钗"/>
<m type="youku" streamtype="flv" src="XMjMxMDQ3MTA4" label="158七十二家房客"/>
<m type="youku" streamtype="flv" src="XMjg0ODYyNDQ0" label="159跟踪孔令学"/>
<m type="youku" streamtype="flv" src="XMTQ5NTAwNDY4" label="160窈窕绅士"/>
<m type="youku" streamtype="flv" src="XMTQzMTYxNjIw" label="161新半斤八两"/>
<m type="youku" streamtype="flv" src="XMTg5Mzc1MDI0" label="162特警新人类"/>
<m type="youku" streamtype="flv" src="XNDk1Njk0NTI=" label="163新扎师妹1"/>
<m type="youku" streamtype="flv" src="XMTM3MjkxNTE2" label="164新扎师妹2"/>
<m type="youku" streamtype="flv" src="XMTQ2NjIyMTAw" label="165新扎师妹3"/>
<m type="youku" streamtype="flv" src="XMTg5Mzc3NzEy" label="166这个夏天有异性"/>
<m type="youku" streamtype="flv" src="XMTQ5MDgxMDI4" label="167救世神棍"/>
<m type="youku" streamtype="flv" src="XMTgzNDgxMjM2" label="168黑豹天下"/>
<m type="youku" streamtype="flv" src="XMTUyNjg2NTIw" label="169丐世英雄"/>
<m type="youku" streamtype="flv" src="XMTg4NTUxNjgw" label="170爱出猫"/>
<m type="youku" streamtype="flv" src="XNTk1ODE4MTI=" label="171六楼后座"/>
<m type="youku" streamtype="flv" src="XMzI0NzQ2NzI0" label="172柠檬可乐"/>
<m type="youku" streamtype="flv" src="XNzcxMjYyODQ=" label="172男歌女唱"/>
<m type="youku" streamtype="flv" src="XMzE5MDk3MjU2" label="173那个不多情"/>
<m type="youku" streamtype="flv" src="XMTgzNTcxMzIw" label="174阿德晒命"/>
<m type="youku" streamtype="flv" src="XNDY2MDQ0MTI=" label="175大踢爆"/>
<m type="youku" streamtype="flv" src="XMzA3Mzk5NDQ0" label="176开心三响炮"/>
<m type="youku" streamtype="flv" src="XMTg5NDExNjI0" label="177基佬四十"/>
<m type="youku" streamtype="flv" src="XMjU1Mzc5NDM2" label="178我爱HK开心万岁"/>
<m type="youku" streamtype="flv" src="XMzI5ODM0ODM2" label="179野蛮秘笈"/>
<m type="youku" streamtype="flv" src="XMTk3MzkwODY4" label="180站直罗别趴下"/>
<m type="youku" streamtype="flv" src="XMjY3MjU5Mzg0" label="181武林女大学生"/>
<m type="youku" streamtype="flv" src="XMTUwNDg0NDQ4" label="182我要做Model"/>
</list>