<list>
<m type="youku" streamtype="flv" src="XMzUyMDMyMzA4" label="¹ÖÏÀÅ·ÑôµÂ 01"/>
<m type="youku" streamtype="flv" src="XMzU3MzgxMDg4" label="¹ÖÏÀÅ·ÑôµÂ 02"/>
<m type="youku" streamtype="flv" src="XMzU3MzgyNjcy" label="¹ÖÏÀÅ·ÑôµÂ 03"/>
<m type="youku" streamtype="flv" src="XMzUyMDM4NTg0" label="¹ÖÏÀÅ·ÑôµÂ 04"/>
<m type="youku" streamtype="flv" src="XMzUyMDQxMTQw" label="¹ÖÏÀÅ·ÑôµÂ 05"/>
<m type="youku" streamtype="flv" src="XMzUyMDQzMjY0" label="¹ÖÏÀÅ·ÑôµÂ 06"/>
<m type="youku" streamtype="flv" src="XMzUyMDQ0MjYw" label="¹ÖÏÀÅ·ÑôµÂ 07"/>
<m type="youku" streamtype="flv" src="XMzUyMDQ1NjE2" label="¹ÖÏÀÅ·ÑôµÂ 08"/>
<m type="youku" streamtype="flv" src="XMzUyMDQ5MjE2" label="¹ÖÏÀÅ·ÑôµÂ 09"/>
<m type="youku" streamtype="flv" src="XMzUyMDUzNDc2" label="¹ÖÏÀÅ·ÑôµÂ 10"/>
<m type="youku" streamtype="flv" src="XMzUyMDU1NTY0" label="¹ÖÏÀÅ·ÑôµÂ 11"/>
<m type="youku" streamtype="flv" src="XMzUyMDU3MjQ0" label="¹ÖÏÀÅ·ÑôµÂ 12"/>
<m type="youku" streamtype="flv" src="XMzUyMDU4MzI4" label="¹ÖÏÀÅ·ÑôµÂ 13"/>
<m type="youku" streamtype="flv" src="XMzUyMDYzNzg0" label="¹ÖÏÀÅ·ÑôµÂ 14"/>
<m type="youku" streamtype="flv" src="XMzUyMDY3NTI4" label="¹ÖÏÀÅ·ÑôµÂ 15"/>
<m type="youku" streamtype="flv" src="XMzUyMDY4Nzk2" label="¹ÖÏÀÅ·ÑôµÂ 16"/>
<m type="youku" streamtype="flv" src="XMzUyMDcxMjAw" label="¹ÖÏÀÅ·ÑôµÂ 17"/>
<m type="youku" streamtype="flv" src="XMzUyMDcyMjIw" label="¹ÖÏÀÅ·ÑôµÂ 18"/>
<m type="youku" streamtype="flv" src="XMzUyMDczMzA0" label="¹ÖÏÀÅ·ÑôµÂ 19"/>
<m type="youku" streamtype="flv" src="XMzUyMDc3MTg4" label="¹ÖÏÀÅ·ÑôµÂ 20"/>
<m type="youku" streamtype="flv" src="XMzUyMDgwNjY4" label="¹ÖÏÀÅ·ÑôµÂ 21"/>
<m type="youku" streamtype="flv" src="XMzUyMDgzNjcy" label="¹ÖÏÀÅ·ÑôµÂ 22"/>
<m type="youku" streamtype="flv" src="XMzUyMDg2MDMy" label="¹ÖÏÀÅ·ÑôµÂ 23"/>
<m type="youku" streamtype="flv" src="XMzUyMDkwMDI4" label="¹ÖÏÀÅ·ÑôµÂ 24"/>
<m type="youku" streamtype="flv" src="XMzUyMDk1NzI0" label="¹ÖÏÀÅ·ÑôµÂ 25"/>
<m type="youku" streamtype="flv" src="XMzUyMDk3MTEy" label="¹ÖÏÀÅ·ÑôµÂ 26"/>
<m type="youku" streamtype="flv" src="XMzUyMDk4MDI4" label="¹ÖÏÀÅ·ÑôµÂ 27"/>
<m type="youku" streamtype="flv" src="XMzUyMDk5Njc2" label="¹ÖÏÀÅ·ÑôµÂ 28"/>
<m type="youku" streamtype="flv" src="XMzUyMTA4MzQ0" label="¹ÖÏÀÅ·ÑôµÂ 29"/>
<m type="youku" streamtype="flv" src="XMzUyMTEwMjQ4" label="¹ÖÏÀÅ·ÑôµÂ 30"/>
<m type="youku" streamtype="flv" src="XMzUyMTExOTI0" label="¹ÖÏÀÅ·ÑôµÂ 31"/>
<m type="youku" streamtype="flv" src="XMzUyMTE5NTU2" label="¹ÖÏÀÅ·ÑôµÂ 32"/>
<m type="youku" streamtype="flv" src="XMzUyMTI2OTAw" label="¹ÖÏÀÅ·ÑôµÂ 33"/>
<m type="youku" streamtype="flv" src="XMzUyMTQyMzgw" label="¹ÖÏÀÅ·ÑôµÂ 34"/>
<m type="youku" streamtype="flv" src="XMzUyMTQ1NDAw" label="¹ÖÏÀÅ·ÑôµÂ 35"/>
<m type="youku" streamtype="flv" src="XMzUyMTUyMDI4" label="¹ÖÏÀÅ·ÑôµÂ 36"/>
<m type="youku" streamtype="flv" src="XMzUyMTU2NTIw" label="¹ÖÏÀÅ·ÑôµÂ 37"/>
<m type="youku" streamtype="flv" src="XMzUyMTY0MDky" label="¹ÖÏÀÅ·ÑôµÂ 38"/>
<m type="youku" streamtype="flv" src="XMzUyMTY4ODAw" label="¹ÖÏÀÅ·ÑôµÂ 39"/>
<m type="youku" streamtype="flv" src="XMzUyMTcwOTM2" label="¹ÖÏÀÅ·ÑôµÂ 40"/>
<m type="youku" streamtype="flv" src="XMzUyMTgwNjMy" label="¹ÖÏÀÅ·ÑôµÂ 41"/>
<m type="youku" streamtype="flv" src="XMzUyMTgzMDU2" label="¹ÖÏÀÅ·ÑôµÂ 42"/>
<m type="youku" streamtype="flv" src="XMzUyMTg4MTQ0" label="¹ÖÏÀÅ·ÑôµÂ 43"/>
<m type="youku" streamtype="flv" src="XMzUyMTk0Mzcy" label="¹ÖÏÀÅ·ÑôµÂ 44"/>
<m type="youku" streamtype="flv" src="XMzUyMTk4MzAw" label="¹ÖÏÀÅ·ÑôµÂ 45"/>
<m type="youku" streamtype="flv" src="XMzUyMjAxNDEy" label="¹ÖÏÀÅ·ÑôµÂ 46"/>
<m type="youku" streamtype="flv" src="XMzUyMjExMjQw" label="¹ÖÏÀÅ·ÑôµÂ 47"/>
<m type="youku" streamtype="flv" src="XMzUyMjEyMjEy" label="¹ÖÏÀÅ·ÑôµÂ 48"/>
<m type="youku" streamtype="flv" src="XMzUyMjIwNTg4" label="¹ÖÏÀÅ·ÑôµÂ 49"/>
<m type="youku" streamtype="flv" src="XMzUyMjIxNzg0" label="¹ÖÏÀÅ·ÑôµÂ 50"/>
<m type="youku" streamtype="flv" src="XMzUyMjI1NjEy" label="¹ÖÏÀÅ·ÑôµÂ 51"/>
<m type="youku" streamtype="flv" src="XMzUyMjI3Nzcy" label="¹ÖÏÀÅ·ÑôµÂ 52"/>
<m type="youku" streamtype="flv" src="XMzUyMjI4NTY0" label="¹ÖÏÀÅ·ÑôµÂ 53"/>
<m type="youku" streamtype="flv" src="XMzUyMjMwNzA4" label="¹ÖÏÀÅ·ÑôµÂ 54"/>
<m type="youku" streamtype="flv" src="XMzUyMjMxMDY4" label="¹ÖÏÀÅ·ÑôµÂ 55"/>
<m type="youku" streamtype="flv" src="XMzUyMjMxNTA4" label="¹ÖÏÀÅ·ÑôµÂ 56"/>
<m type="youku" streamtype="flv" src="XMzUyMjMyNDEy" label="¹ÖÏÀÅ·ÑôµÂ 57"/>
<m type="youku" streamtype="flv" src="XMzUyMjMzNzAw" label="¹ÖÏÀÅ·ÑôµÂ 58"/>
<m type="youku" streamtype="flv" src="XMzUyMjM0MjUy" label="¹ÖÏÀÅ·ÑôµÂ 59"/>
<m type="youku" streamtype="flv" src="XMzUyMjM1MDM2" label="¹ÖÏÀÅ·ÑôµÂ 60"/>
<m type="youku" streamtype="flv" src="XMzUyMjM1ODA4" label="¹ÖÏÀÅ·ÑôµÂ 61"/>
<m type="youku" streamtype="flv" src="XMzUyMjM2MzI0" label="¹ÖÏÀÅ·ÑôµÂ 62"/>
<m type="youku" streamtype="flv" src="XMzUyMjM2ODk2" label="¹ÖÏÀÅ·ÑôµÂ 63"/>
<m type="youku" streamtype="flv" src="XMzUyMjM3MTY4" label="¹ÖÏÀÅ·ÑôµÂ 64"/>
<m type="youku" streamtype="flv" src="XMzUyMjM3NjM2" label="¹ÖÏÀÅ·ÑôµÂ 65"/>
<m type="youku" streamtype="flv" src="XMzUyMjM4Mzgw" label="¹ÖÏÀÅ·ÑôµÂ 66"/>
<m type="youku" streamtype="flv" src="XMzU3NTY4NjAw" label="¹ÖÏÀÅ·ÑôµÂ 67"/>
<m type="youku" streamtype="flv" src="XMzU3NTcwNTQw" label="¹ÖÏÀÅ·ÑôµÂ 68"/>
<m type="youku" streamtype="flv" src="XMzU3NTc1Mjc2" label="¹ÖÏÀÅ·ÑôµÂ 69"/>
</list>