<list>
<m type="youku" streamtype="flv" src="XMTk4MDc1NzM2" label="第01集"/>
<m type="youku" streamtype="flv" src="XMTk4MDc2MDky" label="第02集"/>
<m type="youku" streamtype="flv" src="XMTk4MDc2NTI0" label="第03集"/>
<m type="youku" streamtype="flv" src="XMTk4MDc2OTI0" label="第04集"/>
<m type="youku" streamtype="flv" src="XMTk4MDUzNzc2" label="第05集"/>
<m type="youku" streamtype="flv" src="XMTk4MDU0MjE2" label="第06集"/>
<m type="youku" streamtype="flv" src="XMTk4MDU0Njk2" label="第07集"/>
<m type="youku" streamtype="flv" src="XMTk4MDU1MTky" label="第08集"/>
<m type="youku" streamtype="flv" src="XMTk4MDU1NzI4" label="第09集"/>
<m type="youku" streamtype="flv" src="XMTk4MDU2MTY0" label="第10集"/>
<m type="youku" streamtype="flv" src="XMTk4MDU2NjQ4" label="第11集"/>
<m type="youku" streamtype="flv" src="XMTk4MDU3MTA4" label="第12集"/>
<m type="youku" streamtype="flv" src="XMTk4MDU3NjIw" label="第13集"/>
<m type="youku" streamtype="flv" src="XMTk4MDY2NjM2" label="第14集"/>
<m type="youku" streamtype="flv" src="XMTk4MDU4MTcy" label="第15集"/>
<m type="youku" streamtype="flv" src="XMTk4MDU4NzQ4" label="第16集"/>
<m type="youku" streamtype="flv" src="XMTk4MDU5MTk2" label="第17集"/>
<m type="youku" streamtype="flv" src="XMTk4MDU5NjA0" label="第18集"/>
<m type="youku" streamtype="flv" src="XMTk4MDYwMDY0" label="第19集"/>
<m type="youku" streamtype="flv" src="XMTk4MDYwNTgw" label="第20集"/>
<m type="youku" streamtype="flv" src="XMTk4MDYxMDQ0" label="第21集"/>
<m type="youku" streamtype="flv" src="XMTk4MDYxNTMy" label="第22集"/>
<m type="youku" streamtype="flv" src="XMTk4MDYxOTgw" label="第23集"/>
<m type="youku" streamtype="flv" src="XMTk4MDYyNTAw" label="第24集"/>
<m type="youku" streamtype="flv" src="XMTk4MDYyOTY4" label="第25集"/>
<m type="youku" streamtype="flv" src="XMTk4MDYzNDIw" label="第26集"/>
<m type="youku" streamtype="flv" src="XMTk4MDYzODky" label="第27集"/>
<m type="youku" streamtype="flv" src="XMTk4MDY0MzEy" label="第28集"/>
<m type="youku" streamtype="flv" src="XMTk4MDY0ODAw" label="第29集"/>
<m type="youku" streamtype="flv" src="XMTk4MDY1MTUy" label="第30集"/>
<m type="youku" streamtype="flv" src="XMTk4MDY1NjI0" label="第31集"/>
<m type="youku" streamtype="flv" src="XMTk4MDY2MTQ4" label="第32集"/>
<m type="youku" streamtype="flv" src="XMTk4MDY3MDEy" label="第33集"/>
<m type="youku" streamtype="flv" src="XMTk4MDY4Njg0" label="第34集"/>
<m type="youku" streamtype="flv" src="XMTk4MDY5MTA0" label="第35集"/>
<m type="youku" streamtype="flv" src="XMTk4MDY5NTY4" label="第36集"/>
<m type="youku" streamtype="flv" src="XMTk4MDcwMDAw" label="第37集"/>
<m type="youku" streamtype="flv" src="XMTk4MDcwMzIw" label="第38集"/>
<m type="youku" streamtype="flv" src="XMTk4MDcwNjc2" label="第39集"/>
<m type="youku" streamtype="flv" src="XMTk4MDcwOTcy" label="第40集"/>
<m type="youku" streamtype="flv" src="XMTk4MDcxMjAw" label="第41集"/>
<m type="youku" streamtype="flv" src="XMTk4MDcxNTMy" label="第42集"/>
<m type="youku" streamtype="flv" src="XMTk4MDcxOTA4" label="第43集"/>
<m type="youku" streamtype="flv" src="XMTk4MDcyMzQ0" label="第44集"/>
<m type="youku" streamtype="flv" src="XMTk4MDcyODE2" label="第45集"/>
<m type="youku" streamtype="flv" src="XMTk4MDczMTY4" label="第46集"/>
<m type="youku" streamtype="flv" src="XMTk4MDczNjA4" label="第47集"/>
<m type="youku" streamtype="flv" src="XMTk4MDczOTg4" label="第48集"/>
<m type="youku" streamtype="flv" src="XMTk4MDc0NTEy" label="第49集"/>
<m type="youku" streamtype="flv" src="XMTk4MDc0OTIw" label="第50集"/>
<m type="youku" streamtype="flv" src="XMTk4MDc1MzI0" label="第51集"/>
<m type="youku" streamtype="flv" src="XMTk4MDY3NDQ4" label="第52集"/>
<m type="youku" streamtype="flv" src="XMjc0MDM0Njk2" label="第53集"/>
<m type="youku" streamtype="flv" src="XMTk4MDc3NDQ4" label="第54集"/>
<m type="youku" streamtype="flv" src="XMTk4MDc4MDA4" label="第55集"/>
<m type="youku" streamtype="flv" src="XMTk4MDc4MzYw" label="第56集"/>
<m type="youku" streamtype="flv" src="XMTk4MDc4NzU2" label="第57集"/>
<m type="youku" streamtype="flv" src="XMTk4MDc5MTE2" label="第58集"/>
<m type="youku" streamtype="flv" src="XMTk4MDc5NTI4" label="第59集"/>
<m type="youku" streamtype="flv" src="XMTk4MDc5ODky" label="第60集"/>
<m type="youku" streamtype="flv" src="XMTk4MDgwMzI4" label="第61集"/>
<m type="youku" streamtype="flv" src="XMTk4MDgwNzIw" label="第62集"/>
<m type="youku" streamtype="flv" src="XMTk4MDgxMjM2" label="第63集"/>
<m type="youku" streamtype="flv" src="XMTk4MDgxNzM2" label="第64集"/>
<m type="youku" streamtype="flv" src="XMTk4MDgyMjcy" label="第65集"/>
<m type="youku" streamtype="flv" src="XMTk4MDgyNzY0" label="第66集"/>
<m type="youku" streamtype="flv" src="XMTk4MDgzMTQw" label="第67集"/>
<m type="youku" streamtype="flv" src="XMTk4MDgzNDQ0" label="第68集"/>
<m type="youku" streamtype="flv" src="XMTk4MDgzNzQ0" label="第69集"/>
<m type="youku" streamtype="flv" src="XMTk4MDg0MTAw" label="第70集"/>
<m type="youku" streamtype="flv" src="XMTk4MDg0MzYw" label="第71集"/>
<m type="youku" streamtype="flv" src="XMTk4MDY3ODY4" label="第72集"/>
<m type="youku" streamtype="flv" src="XMTk4MDg0NjAw" label="第73集"/>
<m type="youku" streamtype="flv" src="XMTk4MDg0ODYw" label="第74集"/>
<m type="youku" streamtype="flv" src="XMTk4MDg1MTA4" label="第75集"/>
<m type="youku" streamtype="flv" src="XMTk4MDg1NDg0" label="第76集"/>
<m type="youku" streamtype="flv" src="XMTk4MDg1NzY4" label="第77集"/>
<m type="youku" streamtype="flv" src="XMTk4MDg2MDgw" label="第78集"/>
<m type="youku" streamtype="flv" src="XMTk4MDg2MzI0" label="第79集"/>
<m type="youku" streamtype="flv" src="XMTk4MDg2NjA0" label="第80集"/>
<m type="youku" streamtype="flv" src="XMTk4MDg2ODc2" label="第81集"/>
<m type="youku" streamtype="flv" src="XMTk4MDg3MDg4" label="第82集"/>
<m type="youku" streamtype="flv" src="XMTk4MDg3MzU2" label="第83集"/>
<m type="youku" streamtype="flv" src="XMTk4MDg3NjUy" label="第84集"/>
<m type="youku" streamtype="flv" src="XMTk4MDg3OTcy" label="第85集"/>
<m type="youku" streamtype="flv" src="XMTk4MDg4MjA0" label="第86集"/>
<m type="youku" streamtype="flv" src="XMTk4MDg4NTI0" label="第87集"/>
<m type="youku" streamtype="flv" src="XMTk4MDg4ODYw" label="第88集"/>
<m type="youku" streamtype="flv" src="XMTk4MDg5MTg4" label="第89集"/>
<m type="youku" streamtype="flv" src="XMTk4MDg5NDcy" label="第90集"/>
<m type="youku" streamtype="flv" src="XMTk4MDY4MzEy" label="第91集"/>
<m type="youku" streamtype="flv" src="XMTk4MDg5Nzg0" label="第92集"/>
<m type="youku" streamtype="flv" src="XMTk4MDkwMDc2" label="第93集"/>
<m type="youku" streamtype="flv" src="XMTk4MDkwNDQ0" label="第94集"/>
<m type="youku" streamtype="flv" src="XMTk4MDkwNzE2" label="第95集"/>
</list>