<list>
<m type="youku" streamtype="flv" src="XMTU5MDM0NTQw" label="少年包青天01"/>
<m type="youku" streamtype="flv" src="XMTU5MDM0NTQ0" label="少年包青天02"/>
<m type="youku" streamtype="flv" src="XMTU5MDM0NTQ4" label="少年包青天03"/>
<m type="youku" streamtype="flv" src="XMTU5MDM0NTUy" label="少年包青天04"/>
<m type="youku" streamtype="flv" src="XMTU5MDM0NTU2" label="少年包青天05"/>
<m type="youku" streamtype="flv" src="XMTU5MDM0NTYw" label="少年包青天06"/>
<m type="youku" streamtype="flv" src="XMTU5MDM0NTY0" label="少年包青天07"/>
<m type="youku" streamtype="flv" src="XMTU5MDM0NTY4" label="少年包青天08"/>
<m type="youku" streamtype="flv" src="XMTU5MDM0NTcy" label="少年包青天09"/>
<m type="youku" streamtype="flv" src="XMTU5MDM0NTc2" label="少年包青天10"/>
<m type="youku" streamtype="flv" src="XMTU5MDM0NTgw" label="少年包青天11"/>
<m type="youku" streamtype="flv" src="XMTU5MDM0NTg4" label="少年包青天12"/>
<m type="youku" streamtype="flv" src="XMTU5MDM0NTk2" label="少年包青天13"/>
<m type="youku" streamtype="flv" src="XMTU5MDM0NjAw" label="少年包青天14"/>
<m type="youku" streamtype="flv" src="XMTU5MDM0NjA0" label="少年包青天15"/>
<m type="youku" streamtype="flv" src="XMTU5MDM0NjA4" label="少年包青天16"/>
<m type="youku" streamtype="flv" src="XMTU5MDM0NjEy" label="少年包青天17"/>
<m type="youku" streamtype="flv" src="XMTU5MDM0NjE2" label="少年包青天18"/>
<m type="youku" streamtype="flv" src="XMTU5MDM0NjIw" label="少年包青天19"/>
<m type="youku" streamtype="flv" src="XMTU5MDM0NjI0" label="少年包青天20"/>
<m type="youku" streamtype="flv" src="XMTU5MDM0NzIw" label="少年包青天21"/>
<m type="youku" streamtype="flv" src="XMTU5MDM0NzI0" label="少年包青天22"/>
<m type="youku" streamtype="flv" src="XMTU5MDM0NzI4" label="少年包青天23"/>
<m type="youku" streamtype="flv" src="XMTU5MDM0NzMy" label="少年包青天24"/>
<m type="youku" streamtype="flv" src="XMTU5MDM0NzM2" label="少年包青天25"/>
<m type="youku" streamtype="flv" src="XMTU5MDM0NzQw" label="少年包青天26"/>
<m type="youku" streamtype="flv" src="XMTU5MDM0NzQ0" label="少年包青天27"/>
<m type="youku" streamtype="flv" src="XMTU5MDM0NzQ4" label="少年包青天28"/>
<m type="youku" streamtype="flv" src="XMTU5MDM0NzU2" label="少年包青天29"/>
<m type="youku" streamtype="flv" src="XMTU5MDM0NzYw" label="少年包青天30"/>
<m type="youku" streamtype="flv" src="XMTU5MDM0NzY0" label="少年包青天31"/>
<m type="youku" streamtype="flv" src="XMTU5MDM0NzY4" label="少年包青天32"/>
<m type="youku" streamtype="flv" src="XMTU5MDM0Nzcy" label="少年包青天33"/>
<m type="youku" streamtype="flv" src="XMTU5MDM0Nzc2" label="少年包青天34"/>
<m type="youku" streamtype="flv" src="XMTU5MDM0Nzgw" label="少年包青天35"/>
<m type="youku" streamtype="flv" src="XMTU5MDM0Nzg0" label="少年包青天36"/>
<m type="youku" streamtype="flv" src="XMTU5MDM0Nzg4" label="少年包青天37"/>
<m type="youku" streamtype="flv" src="XMTU5MDM0Nzk2" label="少年包青天38"/>
<m type="youku" streamtype="flv" src="XMTU5MDM0ODAw" label="少年包青天39"/>
<m type="youku" streamtype="flv" src="XMTU5MDM0ODA0" label="少年包青天40"/>
</list>