<list>
<m type="youku" streamtype="flv" src="XMTIxODY5NzE2" label="第01集" />
<m type="youku" streamtype="flv" src="XMTIxODY5Njc2" label="第02集" />
<m type="youku" streamtype="flv" src="XMTIxODY5NzIw" label="第03集" />
<m type="youku" streamtype="flv" src="XMTIxODY5Njgw" label="第04集" />
<m type="youku" streamtype="flv" src="XMTIxODY5Njg0" label="第05集" />
<m type="youku" streamtype="flv" src="XMTIxODY5NzI0" label="第06集" />
<m type="youku" streamtype="flv" src="XMTIxODY5Njg4" label="第07集" />
<m type="youku" streamtype="flv" src="XMTIxODY5Njky" label="第08集" />
<m type="youku" streamtype="flv" src="XMTIxODY5NzI4" label="第09集" />
<m type="youku" streamtype="flv" src="XMTIxODY5NzMy" label="第10集" />
<m type="youku" streamtype="flv" src="XMTIxODY5Njk2" label="第11集" />
<m type="youku" streamtype="flv" src="XMTIxODY5NjU2" label="第12集" />
<m type="youku" streamtype="flv" src="XMTIxODY5NjYw" label="第13集" />
<m type="youku" streamtype="flv" src="XMTIxODY5NjY0" label="第14集" />
<m type="youku" streamtype="flv" src="XMTIxODY5NzAw" label="第15集" />
<m type="youku" streamtype="flv" src="XMTIxODY5NzA0" label="第16集" />
<m type="youku" streamtype="flv" src="XMTIxODY5NzA4" label="第17集" />
<m type="youku" streamtype="flv" src="XMTIxODY5NzEy" label="第18集" />
<m type="youku" streamtype="flv" src="XMTIxODY5NjY4" label="第19集" />
<m type="youku" streamtype="flv" src="XMTIxODY5Njcy" label="第20集" />
<m type="youku" streamtype="flv" src="XMTIxODY5Nzg0" label="第21集" />
<m type="youku" streamtype="flv" src="XMTIxODY5Nzky" label="第22集" />
<m type="youku" streamtype="flv" src="XMTIxODY5Nzg4" label="第23集" />
<m type="youku" streamtype="flv" src="XMTIxODY5Nzk2" label="第24集" />
<m type="youku" streamtype="flv" src="XMTIxODY5ODAw" label="第25集" />
<m type="youku" streamtype="flv" src="XMTIxODY5ODA0" label="第26集" />
<m type="youku" streamtype="flv" src="XMTIxODY5ODA4" label="第27集" />
<m type="youku" streamtype="flv" src="XMTIxODY5ODEy" label="第28集" />
<m type="youku" streamtype="flv" src="XMTIxODY5ODE2" label="第29集" />
<m type="youku" streamtype="flv" src="XMTIxODY5ODQ4" label="第30集" />
<m type="youku" streamtype="flv" src="XMTIxODY5ODUy" label="第31集" />
<m type="youku" streamtype="flv" src="XMTIxODY5ODYw" label="第32集" />
<m type="youku" streamtype="flv" src="XMTIxODY5ODIw" label="第33集" />
<m type="youku" streamtype="flv" src="XMTIxODY5ODI0" label="第34集" />
<m type="youku" streamtype="flv" src="XMTIxODY5ODI4" label="第35集" />
<m type="youku" streamtype="flv" src="XMTIxODY5ODM2" label="第36集" />
<m type="youku" streamtype="flv" src="XMTIxODY5ODY0" label="第37集" />
<m type="youku" streamtype="flv" src="XMTIxODY5ODY4" label="第38集" />
<m type="youku" streamtype="flv" src="XMTIxODY5ODQw" label="第39集" />
<m type="youku" streamtype="flv" src="XMTIxODY5ODQ0" label="第40集" />
</list>